{"parent":"item/template_skull","textures":{"0":"helmet_icon:item/divan_helmet_model","particle":"#0"},"gui_light":"front","elements":[{"from":[4,0,4],"to":[12,8,12],"rotation":{"angle":0,"axis":"y","origin":[8,4,8]},"faces":{"north":{"uv":[6,2,8,4],"texture":"#0"},"east":{"uv":[4,2,6,4],"texture":"#0"},"south":{"uv":[2,2,4,4],"texture":"#0"},"west":{"uv":[0,2,2,4],"texture":"#0"},"up":{"uv":[4,2,2,0],"rotation":180,"texture":"#0"},"down":{"uv":[4,0,6,2],"rotation":180,"texture":"#0"}}},{"from":[3.75,-0.25,3.75],"to":[12.25,8.25,12.25],"rotation":{"angle":0,"axis":"y","origin":[8,4,8]},"faces":{"north":{"uv":[12.25,5.75,14.5,8],"texture":"#0"},"east":{"uv":[10.25,5.75,12.25,8],"texture":"#0"},"south":{"uv":[8,5.75,10.25,8],"texture":"#0"},"west":{"uv":[6,5.75,8,8],"texture":"#0"},"up":{"uv":[10.25,6,8,4],"rotation":180,"texture":"#0"},"down":{"uv":[0,0,0,0],"rotation":90,"texture":"#0"}}},{"name":"horn","from":[0.025,1.025,8.282],"to":[7.025,15.025,8.282],"rotation":{"angle":-22.5,"axis":"y","origin":[3.525,8.025,8.282]},"faces":{"north":{"uv":[1.75,4,0,7.5],"texture":"#0"},"east":{"uv":[0,0,0,0],"texture":"#0"},"south":{"uv":[0,4,1.75,7.5],"texture":"#0"},"west":{"uv":[0,0,0,0],"texture":"#0"},"up":{"uv":[0,0,0,0],"texture":"#0"},"down":{"uv":[0,0,0,0],"texture":"#0"}}},{"name":"horn","from":[8.975,1.025,8.282],"to":[15.975,15.025,8.282],"rotation":{"angle":22.5,"axis":"y","origin":[12.475,8.025,8.282]},"faces":{"north":{"uv":[0,4,1.75,7.5],"texture":"#0"},"east":{"uv":[0,0,0,0],"texture":"#0"},"south":{"uv":[1.75,4,0,7.5],"texture":"#0"},"west":{"uv":[0,0,0,0],"texture":"#0"},"up":{"uv":[0,0,0,0],"texture":"#0"},"down":{"uv":[0,0,0,0],"texture":"#0"}}}]}